Workbook

Sheet Léame
A1: Herramienta de pronóstico de ventas — Asertia Comercial, línea Ferrero
A3: Qué contiene: pronóstico mensual de unidades display de septiembre a noviembre de 2026 por agencia y marca (72 combinaciones por mes, 216 filas).
A4: Modelo: Random Forest con rezago de 12 meses, reentrenado con los datos cerrados hasta agosto de 2026 (ver cuaderno de Colab).
A5: Hojas: Parámetros (celdas amarillas editables), Pronóstico, Totales y Desempeño. Lo calculado con fórmulas se actualiza al cambiar los parámetros.
A6: Alerta: la fila se marca «Revisar» cuando el pronóstico se aleja más del umbral de lo vendido el mismo mes de 2025. Revisarlas a mano antes de pedir.
A7: Confiabilidad y método: salen del WAPE de la marca en la prueba (mayo a agosto de 2026). Conviene revisarlos cada trimestre.
A8: Valor estimado: pronóstico × precio medio de venta por unidad display de 2026. No es costo de inventario ni margen.
A9: Reentrenar al cerrar cada mes con la venta completa.

Sheet Pronóstico
A1: Mes | B1: Agencia | C1: Marca | D1: Pronóstico (u.) | E1: Mismo mes 2025 (u.) | F1: Prom. 3 meses previos (u.) | G1: Variación vs 2025 | H1: Alerta | I1: WAPE de la marca | J1: Banda inferior (u.) | K1: Banda superior (u.) | L1: Confiabilidad | M1: Método recomendado | N1: Precio (US$) | O1: Valor estimado (US$)
A2: Septiembre 2026 | B2: Ambato | C2: Hanuta | D2: 1726.2 | E2: 2366 | F2: 1189.7 | G2: =IF(E2=0,"",D2/E2-1) | H2: =IF(E2=0,IF(D2>0,"Revisar",""),IF(ABS(G2)>Parámetros!$B$3,"Revisar","")) | I2: =INDEX(Desempeño!$C$4:$C$12,MATCH(C2,Desempeño!$A$4:$A$12,0)) | J2: =MAX(0,D2*(1-I2*Parámetros!$B$8)) | K2: =D2*(1+I2*Parámetros!$B$8) | L2: =INDEX(Desempeño!$H$4:$H$12,MATCH(C2,Desempeño!$A$4:$A$12,0)) | M2: =INDEX(Desempeño!$G$4:$G$12,MATCH(C2,Desempeño!$A$4:$A$12,0)) | N2: =INDEX(Parámetros!$B$13:$B$21,MATCH(C2,Parámetros!$A$13:$A$21,0)) | O2: =D2*N2
A3: Septiembre 2026 | B3: Ambato | C3: Kinder Bueno | D3: 1947.3 | E3: 2543 | F3: 1728.3 | G3: =IF(E3=0,"",D3/E3-1) | H3: =IF(E3=0,IF(D3>0,"Revisar",""),IF(ABS(G3)>Parámetros!$B$3,"Revisar","")) | I3: =INDEX(Desempeño!$C$4:$C$12,MATCH(C3,Desempeño!$A$4:$A$12,0)) | J3: =MAX(0,D3*(1-I3*Parámetros!$B$8)) | K3: =D3*(1+I3*Parámetros!$B$8) | L3: =INDEX(Desempeño!$H$4:$H$12,MATCH(C3,Desempeño!$A$4:$A$12,0)) | M3: =INDEX(Desempeño!$G$4:$G$12,MATCH(C3,Desempeño!$A$4:$A$12,0)) | N3: =INDEX(Parámetros!$B$13:$B$21,MATCH(C3,Parámetros!$A$13:$A$21,0)) | O3: =D3*N3
A4: Septiembre 2026 | B4: Ambato | C4: Kinder Chocolate | D4: 558.4 | E4: 743 | F4: 484.7 | G4: =IF(E4=0,"",D4/E4-1) | H4: =IF(E4=0,IF(D4>0,"Revisar",""),IF(ABS(G4)>Parámetros!$B$3,"Revisar","")) | I4: =INDEX(Desempeño!$C$4:$C$12,MATCH(C4,Desempeño!$A$4:$A$12,0)) | J4: =MAX(0,D4*(1-I4*Parámetros!$B$8)) | K4: =D4*(1+I4*Parámetros!$B$8) | L4: =INDEX(Desempeño!$H$4:$H$12,MATCH(C4,Desempeño!$A$4:$A$12,0)) | M4: =INDEX(Desempeño!$G$4:$G$12,MATCH(C4,Desempeño!$A$4:$A$12,0)) | N4: =INDEX(Parámetros!$B$13:$B$21,MATCH(C4,Parámetros!$A$13:$A$21,0)) | O4: =D4*N4
A5: Septiembre 2026 | B5: Ambato | C5: Kinder Joy | D5: 3502.6 | E5: 3158 | F5: 3201 | G5: =IF(E5=0,"",D5/E5-1) | H5: =IF(E5=0,IF(D5>0,"Revisar",""),IF(ABS(G5)>Parámetros!$B$3,"Revisar","")) | I5: =INDEX(Desempeño!$C$4:$C$12,MATCH(C5,Desempeño!$A$4:$A$12,0)) | J5: =MAX(0,D5*(1-I5*Parámetros!$B$8)) | K5: =D5*(1+I5*Parámetros!$B$8) | L5: =INDEX(Desempeño!$H$4:$H$12,MATCH(C5,Desempeño!$A$4:$A$12,0)) | M5: =INDEX(Desempeño!$G$4:$G$12,MATCH(C5,Desempeño!$A$4:$A$12,0)) | N5: =INDEX(Parámetros!$B$13:$B$21,MATCH(C5,Parámetros!$A$13:$A$21,0)) | O5: =D5*N5
A6: Septiembre 2026 | B6: Ambato | C6: Noggy | D6: 1586.1 | E6: 2246 | F6: 1454.7 | G6: =IF(E6=0,"",D6/E6-1) | H6: =IF(E6=0,IF(D6>0,"Revisar",""),IF(ABS(G6)>Parámetros!$B$3,"Revisar","")) | I6: =INDEX(Desempeño!$C$4:$C$12,MATCH(C6,Desempeño!$A$4:$A$12,0)) | J6: =MAX(0,D6*(1-I6*Parámetros!$B$8)) | K6: =D6*(1+I6*Parámetros!$B$8) | L6: =INDEX(Desempeño!$H$4:$H$12,MATCH(C6,Desempeño!$A$4:$A$12,0)) | M6: =INDEX(Desempeño!$G$4:$G$12,MATCH(C6,Desempeño!$A$4:$A$12,0)) | N6: =INDEX(Parámetros!$B$13:$B$21,MATCH(C6,Parámetros!$A$13:$A$21,0)) | O6: =D6*N6
A7: Septiembre 2026 | B7: Ambato | C7: Nutella | D7: 4455.4 | E7: 4674 | F7: 4269.7 | G7: =IF(E7=0,"",D7/E7-1) | H7: =IF(E7=0,IF(D7>0,"Revisar",""),IF(ABS(G7)>Parámetros!$B$3,"Revisar","")) | I7: =INDEX(Desempeño!$C$4:$C$12,MATCH(C7,Desempeño!$A$4:$A$12,0)) | J7: =MAX(0,D7*(1-I7*Parámetros!$B$8)) | K7: =D7*(1+I7*Parámetros!$B$8) | L7: =INDEX(Desempeño!$H$4:$H$12,MATCH(C7,Desempeño!$A$4:$A$12,0)) | M7: =INDEX(Desempeño!$G$4:$G$12,MATCH(C7,Desempeño!$A$4:$A$12,0)) | N7: =INDEX(Parámetros!$B$13:$B$21,MATCH(C7,Parámetros!$A$13:$A$21,0)) | O7: =D7*N7
A8: Septiembre 2026 | B8: Ambato | C8: Raffaello | D8: 818.2 | E8: 844 | F8: 728.7 | G8: =IF(E8=0,"",D8/E8-1) | H8: =IF(E8=0,IF(D8>0,"Revisar",""),IF(ABS(G8)>Parámetros!$B$3,"Revisar","")) | I8: =INDEX(Desempeño!$C$4:$C$12,MATCH(C8,Desempeño!$A$4:$A$12,0)) | J8: =MAX(0,D8*(1-I8*Parámetros!$B$8)) | K8: =D8*(1+I8*Parámetros!$B$8) | L8: =INDEX(Desempeño!$H$4:$H$12,MATCH(C8,Desempeño!$A$4:$A$12,0)) | M8: =INDEX(Desempeño!$G$4:$G$12,MATCH(C8,Desempeño!$A$4:$A$12,0)) | N8: =INDEX(Parámetros!$B$13:$B$21,MATCH(C8,Parámetros!$A$13:$A$21,0)) | O8: =D8*N8
A9: Septiembre 2026 | B9: Ambato | C9: Rocher | D9: 4002.7 | E9: 5638 | F9: 3457.7 | G9: =IF(E9=0,"",D9/E9-1) | H9: =IF(E9=0,IF(D9>0,"Revisar",""),IF(ABS(G9)>Parámetros!$B$3,"Revisar","")) | I9: =INDEX(Desempeño!$C$4:$C$12,MATCH(C9,Desempeño!$A$4:$A$12,0)) | J9: =MAX(0,D9*(1-I9*Parámetros!$B$8)) | K9: =D9*(1+I9*Parámetros!$B$8) | L9: =INDEX(Desempeño!$H$4:$H$12,MATCH(C9,Desempeño!$A$4:$A$12,0)) | M9: =INDEX(Desempeño!$G$4:$G$12,MATCH(C9,Desempeño!$A$4:$A$12,0)) | N9: =INDEX(Parámetros!$B$13:$B$21,MATCH(C9,Parámetros!$A$13:$A$21,0)) | O9: =D9*N9
A10: Septiembre 2026 | B10: Ambato | C10: Tic Tac | D10: 1857.6 | E10: 2433 | F10: 1572 | G10: =IF(E10=0,"",D10/E10-1) | H10: =IF(E10=0,IF(D10>0,"Revisar",""),IF(ABS(G10)>Parámetros!$B$3,"Revisar","")) | I10: =INDEX(Desempeño!$C$4:$C$12,MATCH(C10,Desempeño!$A$4:$A$12,0)) | J10: =MAX(0,D10*(1-I10*Parámetros!$B$8)) | K10: =D10*(1+I10*Parámetros!$B$8) | L10: =INDEX(Desempeño!$H$4:$H$12,MATCH(C10,Desempeño!$A$4:$A$12,0)) | M10: =INDEX(Desempeño!$G$4:$G$12,MATCH(C10,Desempeño!$A$4:$A$12,0)) | N10: =INDEX(Parámetros!$B$13:$B$21,MATCH(C10,Parámetros!$A$13:$A$21,0)) | O10: =D10*N10
A11: Septiembre 2026 | B11: Cuenca | C11: Hanuta | D11: 2732.4 | E11: 3498 | F11: 2328 | G11: =IF(E11=0,"",D11/E11-1) | H11: =IF(E11=0,IF(D11>0,"Revisar",""),IF(ABS(G11)>Parámetros!$B$3,"Revisar","")) | I11: =INDEX(Desempeño!$C$4:$C$12,MATCH(C11,Desempeño!$A$4:$A$12,0)) | J11: =MAX(0,D11*(1-I11*Parámetros!$B$8)) | K11: =D11*(1+I11*Parámetros!$B$8) | L11: =INDEX(Desempeño!$H$4:$H$12,MATCH(C11,Desempeño!$A$4:$A$12,0)) | M11: =INDEX(Desempeño!$G$4:$G$12,MATCH(C11,Desempeño!$A$4:$A$12,0)) | N11: =INDEX(Parámetros!$B$13:$B$21,MATCH(C11,Parámetros!$A$13:$A$21,0)) | O11: =D11*N11
A12: Septiembre 2026 | B12: Cuenca | C12: Kinder Bueno | D12: 4846 | E12: 4937 | F12: 5227.7 | G12: =IF(E12=0,"",D12/E12-1) | H12: =IF(E12=0,IF(D12>0,"Revisar",""),IF(ABS(G12)>Parámetros!$B$3,"Revisar","")) | I12: =INDEX(Desempeño!$C$4:$C$12,MATCH(C12,Desempeño!$A$4:$A$12,0)) | J12: =MAX(0,D12*(1-I12*Parámetros!$B$8)) | K12: =D12*(1+I12*Parámetros!$B$8) | L12: =INDEX(Desempeño!$H$4:$H$12,MATCH(C12,Desempeño!$A$4:$A$12,0)) | M12: =INDEX(Desempeño!$G$4:$G$12,MATCH(C12,Desempeño!$A$4:$A$12,0)) | N12: =INDEX(Parámetros!$B$13:$B$21,MATCH(C12,Parámetros!$A$13:$A$21,0)) | O12: =D12*N12
A13: Septiembre 2026 | B13: Cuenca | C13: Kinder Chocolate | D13: 927.8 | E13: 1243 | F13: 1050.7 | G13: =IF(E13=0,"",D13/E13-1) | H13: =IF(E13=0,IF(D13>0,"Revisar",""),IF(ABS(G13)>Parámetros!$B$3,"Revisar","")) | I13: =INDEX(Desempeño!$C$4:$C$12,MATCH(C13,Desempeño!$A$4:$A$12,0)) | J13: =MAX(0,D13*(1-I13*Parámetros!$B$8)) | K13: =D13*(1+I13*Parámetros!$B$8) | L13: =INDEX(Desempeño!$H$4:$H$12,MATCH(C13,Desempeño!$A$4:$A$12,0)) | M13: =INDEX(Desempeño!$G$4:$G$12,MATCH(C13,Desempeño!$A$4:$A$12,0)) | N13: =INDEX(Parámetros!$B$13:$B$21,MATCH(C13,Parámetros!$A$13:$A$21,0)) | O13: =D13*N13
... A217: Noviembre 2026 | B217: Santo Domingo | C217: Tic Tac | D217: 913.7 | E217: 999 | F217: 806.7 | G217: =IF(E217=0,"",D217/E217-1) | H217: =IF(E217=0,IF(D217>0,"Revisar",""),IF(ABS(G217)>Parámetros!$B$3,"Revisar","")) | I217: =INDEX(Desempeño!$C$4:$C$12,MATCH(C217,Desempeño!$A$4:$A$12,0)) | J217: =MAX(0,D217*(1-I217*Parámetros!$B$8)) | K217: =D217*(1+I217*Parámetros!$B$8) | L217: =INDEX(Desempeño!$H$4:$H$12,MATCH(C217,Desempeño!$A$4:$A$12,0)) | M217: =INDEX(Desempeño!$G$4:$G$12,MATCH(C217,Desempeño!$A$4:$A$12,0)) | N217: =INDEX(Parámetros!$B$13:$B$21,MATCH(C217,Parámetros!$A$13:$A$21,0)) | O217: =D217*N217

Sheet Totales
A1: Pronóstico nacional por mes
A3: Mes | B3: Pronóstico (u.) | C3: Mismo mes 2025 (u.) | D3: Variación | E3: Valor (millones US$) | F3: Filas con alerta
A4: Septiembre 2026 | B4: =SUMIFS(Pronóstico!$D$2:$D$217,Pronóstico!$A$2:$A$217,A4) | C4: =SUMIFS(Pronóstico!$E$2:$E$217,Pronóstico!$A$2:$A$217,A4) | D4: =B4/C4-1 | E4: =SUMIFS(Pronóstico!$O$2:$O$217,Pronóstico!$A$2:$A$217,A4)/1000000 | F4: =COUNTIFS(Pronóstico!$A$2:$A$217,A4,Pronóstico!$H$2:$H$217,"Revisar")&" de "&COUNTIFS(Pronóstico!$A$2:$A$217,A4)
A5: Octubre 2026 | B5: =SUMIFS(Pronóstico!$D$2:$D$217,Pronóstico!$A$2:$A$217,A5) | C5: =SUMIFS(Pronóstico!$E$2:$E$217,Pronóstico!$A$2:$A$217,A5) | D5: =B5/C5-1 | E5: =SUMIFS(Pronóstico!$O$2:$O$217,Pronóstico!$A$2:$A$217,A5)/1000000 | F5: =COUNTIFS(Pronóstico!$A$2:$A$217,A5,Pronóstico!$H$2:$H$217,"Revisar")&" de "&COUNTIFS(Pronóstico!$A$2:$A$217,A5)
A6: Noviembre 2026 | B6: =SUMIFS(Pronóstico!$D$2:$D$217,Pronóstico!$A$2:$A$217,A6) | C6: =SUMIFS(Pronóstico!$E$2:$E$217,Pronóstico!$A$2:$A$217,A6) | D6: =B6/C6-1 | E6: =SUMIFS(Pronóstico!$O$2:$O$217,Pronóstico!$A$2:$A$217,A6)/1000000 | F6: =COUNTIFS(Pronóstico!$A$2:$A$217,A6,Pronóstico!$H$2:$H$217,"Revisar")&" de "&COUNTIFS(Pronóstico!$A$2:$A$217,A6)
A9: Pronóstico por marca (u.)
A10: Marca | B10: Septiembre 2026 | C10: Octubre 2026 | D10: Noviembre 2026
A11: Hanuta | B11: =SUMIFS(Pronóstico!$D$2:$D$217,Pronóstico!$C$2:$C$217,$A11,Pronóstico!$A$2:$A$217,B$10) | C11: =SUMIFS(Pronóstico!$D$2:$D$217,Pronóstico!$C$2:$C$217,$A11,Pronóstico!$A$2:$A$217,C$10) | D11: =SUMIFS(Pronóstico!$D$2:$D$217,Pronóstico!$C$2:$C$217,$A11,Pronóstico!$A$2:$A$217,D$10)
A12: Kinder Bueno | B12: =SUMIFS(Pronóstico!$D$2:$D$217,Pronóstico!$C$2:$C$217,$A12,Pronóstico!$A$2:$A$217,B$10) | C12: =SUMIFS(Pronóstico!$D$2:$D$217,Pronóstico!$C$2:$C$217,$A12,Pronóstico!$A$2:$A$217,C$10) | D12: =SUMIFS(Pronóstico!$D$2:$D$217,Pronóstico!$C$2:$C$217,$A12,Pronóstico!$A$2:$A$217,D$10)
A13: Kinder Chocolate | B13: =SUMIFS(Pronóstico!$D$2:$D$217,Pronóstico!$C$2:$C$217,$A13,Pronóstico!$A$2:$A$217,B$10) | C13: =SUMIFS(Pronóstico!$D$2:$D$217,Pronóstico!$C$2:$C$217,$A13,Pronóstico!$A$2:$A$217,C$10) | D13: =SUMIFS(Pronóstico!$D$2:$D$217,Pronóstico!$C$2:$C$217,$A13,Pronóstico!$A$2:$A$217,D$10)
A14: Kinder Joy | B14: =SUMIFS(Pronóstico!$D$2:$D$217,Pronóstico!$C$2:$C$217,$A14,Pronóstico!$A$2:$A$217,B$10) | C14: =SUMIFS(Pronóstico!$D$2:$D$217,Pronóstico!$C$2:$C$217,$A14,Pronóstico!$A$2:$A$217,C$10) | D14: =SUMIFS(Pronóstico!$D$2:$D$217,Pronóstico!$C$2:$C$217,$A14,Pronóstico!$A$2:$A$217,D$10)
A15: Noggy | B15: =SUMIFS(Pronóstico!$D$2:$D$217,Pronóstico!$C$2:$C$217,$A15,Pronóstico!$A$2:$A$217,B$10) | C15: =SUMIFS(Pronóstico!$D$2:$D$217,Pronóstico!$C$2:$C$217,$A15,Pronóstico!$A$2:$A$217,C$10) | D15: =SUMIFS(Pronóstico!$D$2:$D$217,Pronóstico!$C$2:$C$217,$A15,Pronóstico!$A$2:$A$217,D$10)
A16: Nutella | B16: =SUMIFS(Pronóstico!$D$2:$D$217,Pronóstico!$C$2:$C$217,$A16,Pronóstico!$A$2:$A$217,B$10) | C16: =SUMIFS(Pronóstico!$D$2:$D$217,Pronóstico!$C$2:$C$217,$A16,Pronóstico!$A$2:$A$217,C$10) | D16: =SUMIFS(Pronóstico!$D$2:$D$217,Pronóstico!$C$2:$C$217,$A16,Pronóstico!$A$2:$A$217,D$10)
A17: Raffaello | B17: =SUMIFS(Pronóstico!$D$2:$D$217,Pronóstico!$C$2:$C$217,$A17,Pronóstico!$A$2:$A$217,B$10) | C17: =SUMIFS(Pronóstico!$D$2:$D$217,Pronóstico!$C$2:$C$217,$A17,Pronóstico!$A$2:$A$217,C$10) | D17: =SUMIFS(Pronóstico!$D$2:$D$217,Pronóstico!$C$2:$C$217,$A17,Pronóstico!$A$2:$A$217,D$10)
A18: Rocher | B18: =SUMIFS(Pronóstico!$D$2:$D$217,Pronóstico!$C$2:$C$217,$A18,Pronóstico!$A$2:$A$217,B$10) | C18: =SUMIFS(Pronóstico!$D$2:$D$217,Pronóstico!$C$2:$C$217,$A18,Pronóstico!$A$2:$A$217,C$10) | D18: =SUMIFS(Pronóstico!$D$2:$D$217,Pronóstico!$C$2:$C$217,$A18,Pronóstico!$A$2:$A$217,D$10)
A19: Tic Tac | B19: =SUMIFS(Pronóstico!$D$2:$D$217,Pronóstico!$C$2:$C$217,$A19,Pronóstico!$A$2:$A$217,B$10) | C19: =SUMIFS(Pronóstico!$D$2:$D$217,Pronóstico!$C$2:$C$217,$A19,Pronóstico!$A$2:$A$217,C$10) | D19: =SUMIFS(Pronóstico!$D$2:$D$217,Pronóstico!$C$2:$C$217,$A19,Pronóstico!$A$2:$A$217,D$10)
A21: Pronóstico por agencia (u.)
A22: Agencia | B22: Septiembre 2026 | C22: Octubre 2026 | D22: Noviembre 2026
A23: Ambato | B23: =SUMIFS(Pronóstico!$D$2:$D$217,Pronóstico!$B$2:$B$217,$A23,Pronóstico!$A$2:$A$217,B$22) | C23: =SUMIFS(Pronóstico!$D$2:$D$217,Pronóstico!$B$2:$B$217,$A23,Pronóstico!$A$2:$A$217,C$22) | D23: =SUMIFS(Pronóstico!$D$2:$D$217,Pronóstico!$B$2:$B$217,$A23,Pronóstico!$A$2:$A$217,D$22)
A24: Cuenca | B24: =SUMIFS(Pronóstico!$D$2:$D$217,Pronóstico!$B$2:$B$217,$A24,Pronóstico!$A$2:$A$217,B$22) | C24: =SUMIFS(Pronóstico!$D$2:$D$217,Pronóstico!$B$2:$B$217,$A24,Pronóstico!$A$2:$A$217,C$22) | D24: =SUMIFS(Pronóstico!$D$2:$D$217,Pronóstico!$B$2:$B$217,$A24,Pronóstico!$A$2:$A$217,D$22)
A25: Guayaquil | B25: =SUMIFS(Pronóstico!$D$2:$D$217,Pronóstico!$B$2:$B$217,$A25,Pronóstico!$A$2:$A$217,B$22) | C25: =SUMIFS(Pronóstico!$D$2:$D$217,Pronóstico!$B$2:$B$217,$A25,Pronóstico!$A$2:$A$217,C$22) | D25: =SUMIFS(Pronóstico!$D$2:$D$217,Pronóstico!$B$2:$B$217,$A25,Pronóstico!$A$2:$A$217,D$22)
A26: Ibarra | B26: =SUMIFS(Pronóstico!$D$2:$D$217,Pronóstico!$B$2:$B$217,$A26,Pronóstico!$A$2:$A$217,B$22) | C26: =SUMIFS(Pronóstico!$D$2:$D$217,Pronóstico!$B$2:$B$217,$A26,Pronóstico!$A$2:$A$217,C$22) | D26: =SUMIFS(Pronóstico!$D$2:$D$217,Pronóstico!$B$2:$B$217,$A26,Pronóstico!$A$2:$A$217,D$22)
A27: Lago Agrio | B27: =SUMIFS(Pronóstico!$D$2:$D$217,Pronóstico!$B$2:$B$217,$A27,Pronóstico!$A$2:$A$217,B$22) | C27: =SUMIFS(Pronóstico!$D$2:$D$217,Pronóstico!$B$2:$B$217,$A27,Pronóstico!$A$2:$A$217,C$22) | D27: =SUMIFS(Pronóstico!$D$2:$D$217,Pronóstico!$B$2:$B$217,$A27,Pronóstico!$A$2:$A$217,D$22)
A28: Manta | B28: =SUMIFS(Pronóstico!$D$2:$D$217,Pronóstico!$B$2:$B$217,$A28,Pronóstico!$A$2:$A$217,B$22) | C28: =SUMIFS(Pronóstico!$D$2:$D$217,Pronóstico!$B$2:$B$217,$A28,Pronóstico!$A$2:$A$217,C$22) | D28: =SUMIFS(Pronóstico!$D$2:$D$217,Pronóstico!$B$2:$B$217,$A28,Pronóstico!$A$2:$A$217,D$22)
A29: Quito | B29: =SUMIFS(Pronóstico!$D$2:$D$217,Pronóstico!$B$2:$B$217,$A29,Pronóstico!$A$2:$A$217,B$22) | C29: =SUMIFS(Pronóstico!$D$2:$D$217,Pronóstico!$B$2:$B$217,$A29,Pronóstico!$A$2:$A$217,C$22) | D29: =SUMIFS(Pronóstico!$D$2:$D$217,Pronóstico!$B$2:$B$217,$A29,Pronóstico!$A$2:$A$217,D$22)
A30: Santo Domingo | B30: =SUMIFS(Pronóstico!$D$2:$D$217,Pronóstico!$B$2:$B$217,$A30,Pronóstico!$A$2:$A$217,B$22) | C30: =SUMIFS(Pronóstico!$D$2:$D$217,Pronóstico!$B$2:$B$217,$A30,Pronóstico!$A$2:$A$217,C$22) | D30: =SUMIFS(Pronóstico!$D$2:$D$217,Pronóstico!$B$2:$B$217,$A30,Pronóstico!$A$2:$A$217,D$22)

Sheet Desempeño
A1: WAPE de la prueba (mayo a agosto de 2026), por agencia, marca y mes
A3: Marca | B3: Unidades vendidas | C3: Modelo | D3: Mes anterior | E3: Año anterior | F3: Prom. móvil 3 | G3: Método recomendado | H3: Confiabilidad
A4: Kinder Chocolate | B4: 20570.042 | C4: 0.151 | D4: 0.227 | E4: 0.24 | F4: 0.174 | G4: =IF(C4-E4>=Parámetros!$B$6,"Venta del mismo mes del año anterior",IF(C4>Parámetros!$B$7,"Modelo, con pedidos pequeños y frecuentes","Modelo")) | H4: =IF(C4<=Parámetros!$B$4,"Alta",IF(C4<=Parámetros!$B$5,"Media","Baja"))
A5: Tic Tac | B5: 63721 | C5: 0.173 | D5: 0.236 | E5: 0.217 | F5: 0.181 | G5: =IF(C5-E5>=Parámetros!$B$6,"Venta del mismo mes del año anterior",IF(C5>Parámetros!$B$7,"Modelo, con pedidos pequeños y frecuentes","Modelo")) | H5: =IF(C5<=Parámetros!$B$4,"Alta",IF(C5<=Parámetros!$B$5,"Media","Baja"))
A6: Kinder Bueno | B6: 68720.333 | C6: 0.196 | D6: 0.284 | E6: 0.265 | F6: 0.182 | G6: =IF(C6-E6>=Parámetros!$B$6,"Venta del mismo mes del año anterior",IF(C6>Parámetros!$B$7,"Modelo, con pedidos pequeños y frecuentes","Modelo")) | H6: =IF(C6<=Parámetros!$B$4,"Alta",IF(C6<=Parámetros!$B$5,"Media","Baja"))
A7: Nutella | B7: 248795.15 | C7: 0.237 | D7: 0.273 | E7: 0.246 | F7: 0.227 | G7: =IF(C7-E7>=Parámetros!$B$6,"Venta del mismo mes del año anterior",IF(C7>Parámetros!$B$7,"Modelo, con pedidos pequeños y frecuentes","Modelo")) | H7: =IF(C7<=Parámetros!$B$4,"Alta",IF(C7<=Parámetros!$B$5,"Media","Baja"))
A8: Kinder Joy | B8: 142473.75 | C8: 0.262 | D8: 0.298 | E8: 0.297 | F8: 0.245 | G8: =IF(C8-E8>=Parámetros!$B$6,"Venta del mismo mes del año anterior",IF(C8>Parámetros!$B$7,"Modelo, con pedidos pequeños y frecuentes","Modelo")) | H8: =IF(C8<=Parámetros!$B$4,"Alta",IF(C8<=Parámetros!$B$5,"Media","Baja"))
A9: Rocher | B9: 175906.56 | C9: 0.342 | D9: 0.445 | E9: 0.224 | F9: 0.512 | G9: =IF(C9-E9>=Parámetros!$B$6,"Venta del mismo mes del año anterior",IF(C9>Parámetros!$B$7,"Modelo, con pedidos pequeños y frecuentes","Modelo")) | H9: =IF(C9<=Parámetros!$B$4,"Alta",IF(C9<=Parámetros!$B$5,"Media","Baja"))
A10: Hanuta | B10: 51062 | C10: 0.417 | D10: 0.432 | E10: 0.521 | F10: 0.358 | G10: =IF(C10-E10>=Parámetros!$B$6,"Venta del mismo mes del año anterior",IF(C10>Parámetros!$B$7,"Modelo, con pedidos pequeños y frecuentes","Modelo")) | H10: =IF(C10<=Parámetros!$B$4,"Alta",IF(C10<=Parámetros!$B$5,"Media","Baja"))
A11: Raffaello | B11: 41606.125 | C11: 0.465 | D11: 0.636 | E11: 0.341 | F11: 0.591 | G11: =IF(C11-E11>=Parámetros!$B$6,"Venta del mismo mes del año anterior",IF(C11>Parámetros!$B$7,"Modelo, con pedidos pequeños y frecuentes","Modelo")) | H11: =IF(C11<=Parámetros!$B$4,"Alta",IF(C11<=Parámetros!$B$5,"Media","Baja"))
A12: Noggy | B12: 82191 | C12: 0.495 | D12: 0.402 | E12: 0.803 | F12: 0.409 | G12: =IF(C12-E12>=Parámetros!$B$6,"Venta del mismo mes del año anterior",IF(C12>Parámetros!$B$7,"Modelo, con pedidos pequeños y frecuentes","Modelo")) | H12: =IF(C12<=Parámetros!$B$4,"Alta",IF(C12<=Parámetros!$B$5,"Media","Baja"))

Sheet Parámetros
A1: Parámetros (celdas amarillas editables)
A3: Umbral de alerta frente al mismo mes de 2025 | B3: 0.3
A4: WAPE máximo para confiabilidad «Alta» | B4: 0.2
A5: WAPE máximo para confiabilidad «Media» | B5: 0.4
A6: Ventaja mínima del año anterior sobre el modelo (puntos de WAPE) | B6: 0.1
A7: WAPE desde el cual se piden lotes pequeños y frecuentes | B7: 0.4
A8: Factor de la banda (× WAPE de la marca) | B8: 1
A11: Precio medio por unidad display, 2026 (US$)
A12: Marca | B12: Precio (US$)
A13: Hanuta | B13: 5.2239
A14: Kinder Bueno | B14: 3.2362
A15: Kinder Chocolate | B15: 7.2335
A16: Kinder Joy | B16: 10.6448
A17: Noggy | B17: 2.5871
A18: Nutella | B18: 5.0536
A19: Raffaello | B19: 4.2254
A20: Rocher | B20: 4.8728
A21: Tic Tac | B21: 5.2803
